example_magic/__init__.py
example_magic/abracadabra.py
example_magic-0.1.2.dist-info/LICENSE
example_magic-0.1.2.dist-info/METADATA
example_magic-0.1.2.dist-info/WHEEL
example_magic-0.1.2.dist-info/top_level.txt
example_magic-0.1.2.dist-info/RECORD
