Metadata-Version: 2.1
Name: example-magic
Version: 0.1.2
Summary: Example IPython magic extension (used for testing)
Home-page: https://github.com/btel/example_magic
Author: Bartosz Telenczuk and IPython Development Team
Author-email: bartosz@telenczuk.pl
License: UNKNOWN
Platform: UNKNOWN
Classifier: Framework :: IPython
Classifier: Programming Language :: Python :: 3
Requires-Python: >=3.1
